Metadata-Version: 2.1
Name: django-stubs-pr730
Version: 1.8.1
Summary: Mypy stubs for Django (with PR #730 merged)
Home-page: https://github.com/typeddjango/django-stubs
Author: Maksim Kurnikov
Author-email: maxim.kurnikov@gmail.com
License: MIT
Project-URL: Release notes, https://github.com/typeddjango/django-stubs/releases
Platform: UNKNOWN
Classifier: License :: OSI Approved :: MIT License
Classifier: Operating System :: OS Independent
Classifier: Programming Language :: Python :: 3.6
Classifier: Programming Language :: Python :: 3.7
Classifier: Programming Language :: Python :: 3.8
Classifier: Programming Language :: Python :: 3.9
Classifier: Typing :: Typed
Classifier: Framework :: Django
Classifier: Framework :: Django :: 2.2
Classifier: Framework :: Django :: 3.0
Classifier: Framework :: Django :: 3.1
Requires-Python: >=3.6
License-File: LICENSE.txt
